cnrpc/__init__.py
cnrpc/cnrpcClient.py
cnrpc/cnrpcServer.py
cnrpc/method.py
cnrpc-0.0.3a0.dist-info/DESCRIPTION.rst
cnrpc-0.0.3a0.dist-info/METADATA
cnrpc-0.0.3a0.dist-info/RECORD
cnrpc-0.0.3a0.dist-info/WHEEL
cnrpc-0.0.3a0.dist-info/metadata.json
cnrpc-0.0.3a0.dist-info/top_level.txt
